git_branch_syncer/__init__.py
git_branch_syncer/syncer.py
git_branch_syncer-0.1.1.dist-info/licenses/LICENSE
git_branch_syncer-0.1.1.dist-info/METADATA
git_branch_syncer-0.1.1.dist-info/WHEEL
git_branch_syncer-0.1.1.dist-info/entry_points.txt
git_branch_syncer-0.1.1.dist-info/top_level.txt
git_branch_syncer-0.1.1.dist-info/RECORD
